README.md
setup.py
frane/__init__.py
frane/frane.py
frane/helpers.py
frane/thresholds.py
frane.egg-info/PKG-INFO
frane.egg-info/SOURCES.txt
frane.egg-info/dependency_links.txt
frane.egg-info/requires.txt
frane.egg-info/top_level.txt