Metadata-Version: 2.1
Name: frane
Version: 0.1.0
Summary: Unsupervised Feature Ranking via Attribute Networks
Home-page: https://github.com/FRANe-team/FRANe
Author: Blaž Šrklj, Urh Primožič, Matej Petkovič
Author-email: urh.primozic@student.fmf.uni-lj.si
License: BSD 2-clause
Platform: UNKNOWN
Classifier: Development Status :: 1 - Planning
Classifier: Intended Audience :: Science/Research
Classifier: License :: OSI Approved :: BSD License
Classifier: Operating System :: POSIX :: Linux
Classifier: Programming Language :: Python :: 2
Classifier: Programming Language :: Python :: 2.7
Classifier: Programming Language :: Python :: 3
Classifier: Programming Language :: Python :: 3.4
Classifier: Programming Language :: Python :: 3.5
